Workbook

Sheet 01 Tender & Timeline
A1: 01 Tender & Timeline Header
A2: Yellow cells = nothing was found in the report - please fill in. All cells are editable.
A4: FIELD | B4: DETAILS SCMD/TET/2026/014 [sample_tet_report.docx]
A5: Tender No | B5: SCMD/TET/2026/014
A6: User Department | B6: Network Operations
A7: Forwarded by | B7: Mr. K. Silva, CXO - Network
A8: Budget Confirmed | B8: CAPEX: LKR 48,000,000 OPEX: -
A9: Previous JTB Reference (if any) | B9: JTB Ref No: Date:
A10: Tender Published Date | B10: 03-08-2026
A11: Tender Closed Date | B11: 24-08-2026
A12: Technical Bid Opened Date | B12: 25-08-2026
A13: TET Report Submission Date
A14: Bid Bond Expiry Date(s) | B14: 24-11-2026 (ABC); 30-11-2026 (XYZ); 27-11-2026 (Delta)
A15: Method of Tendering | B15: Open Tender
A16: Purpose of Tender
A17: Short Description of Goods/Services | B17: Supply, installation, commissioning and training for 4 x 60kVA UPS units with 36-month warranty. Delivery within 12 weeks. etc ...

Sheet 02 Background Summary
A1: 02 Background Summary
A2: Yellow cells = nothing was found in the report - please fill in. All cells are editable.
A4: FIELD | B4: DETAILS SCMD/TET/2026/014 [sample_tet_report.docx]
A5: How the need arose | B5: Existing UPS units reached end of life; replacement required under the DC upgrade project. extend etc. … etc…..
A6: Relevant Approval | B6: Governance Board approval GB/2026/18 dated 12-06-2026.
A7: Project No. & Name | B7: PRJ-2026-044 Regional DC Upgrade
A8: Account Code & Cost Center | B8: N/A (CAPEX)
A9: Budget Reserved/Total Available | B9: LKR 48M of LKR 120M
A10: Procurement process up to bid opening | B10: Tender floated 03-08-2026; bidders' conference 10-08-2026; one 5-day extension; closed 24-08-2026; opened 25-08-2026. Tender Timeline

Sheet 03 Bidder Details
A1: 3. Bidder Details Table (key comparison table)
A2: Yellow cells = nothing was found in the report - please fill in. All cells are editable.
A4: Report: SCMD/TET/2026/014 [sample_tet_report.docx]
A5: FIELD | B5: BIDDER 1 ABC Power (Pvt) Ltd | C5: BIDDER 2 XYZ Energy Solutions | D5: BIDDER 3 Delta Power Ltd
A6: Bidder's Name | B6: ABC Power (Pvt) Ltd | C6: XYZ Energy Solutions | D6: Delta Power Ltd
A7: Local Agent | B7: Yes - Mr. Fernando | C7: No | D7: Yes - Ms. Perera
A8: Letter of Authority (Yes/No) | B8: Yes | C8: No | D8: Yes
A9: Product Brand & Model | B9: Eaton 93PM 60kVA | C9: Schneider Galaxy VS 60kVA | D9: Vertiv Liebert APM 60kVA
A10: Bid Validity (as stated in bid) | B10: 120 days | C10: 90 days | D10: 120 days
A11: Bid Bond Expiry Date | B11: 24-11-2026 | C11: 30-11-2026 | D11: 27-11-2026

Sheet 04 Compliance Evaluation
A1: 4. Compliance Evaluation Table
A2: Yellow cells = nothing was found in the report - please fill in. All cells are editable.
A4: Report: SCMD/TET/2026/014 [sample_tet_report.docx]
A5: FIELD | B5: BIDDER 1 ABC Power (Pvt) Ltd | C5: BIDDER 2 XYZ Energy Solutions | D5: BIDDER 3 Delta Power Ltd
A6: Compliance with General Conditions
A7: Compliance with Technical Conditions
A8: Compliance with Special Conditions
A9: Compliance with Contract Conditions
A10: Major Non-compliances (disqualifying)
A11: Minor/Acceptable Non-compliances | B11: 3-year warranty quoted instead of 5-year
A12: Impact of Non-compliances | C12: Cannot meet the critical backup requirement
A13: Qualified / Disqualified | B13: Qualified | C13: Disqualified | D13: Qualified
A14: Commercial terms to be negotiated (non-compliance to financial terms) | B14: payment terms to be revised to 30/60/10 | D14: LD clause to be negotiated
A15: OVERALL: Compliant / Non-compliant (auto) | B15: =IF(AND(COUNTA(B6:B9)=0,B10=""),"",IF(OR(COUNTIF(B6:B9,"Non-compliant")>0,AND(B10<>"",ISERROR(MATCH(LOWER(TRIM(B10)),{"none","nil","n/a","-","no"},0)))),"Non-compliant","Compliant")) | C15: =IF(AND(COUNTA(C6:C9)=0,C10=""),"",IF(OR(COUNTIF(C6:C9,"Non-compliant")>0,AND(C10<>"",ISERROR(MATCH(LOWER(TRIM(C10)),{"none","nil","n/a","-","no"},0)))),"Non-compliant","Compliant")) | D15: =IF(AND(COUNTA(D6:D9)=0,D10=""),"",IF(OR(COUNTIF(D6:D9,"Non-compliant")>0,AND(D10<>"",ISERROR(MATCH(LOWER(TRIM(D10)),{"none","nil","n/a","-","no"},0)))),"Non-compliant","Compliant"))

Sheet 05 Commercial Evaluation
A1: 5. Recommendations for Commercial Evaluation
A2: Yellow cells = nothing was found in the report - please fill in. All cells are editable.
A4: Report: SCMD/TET/2026/014 [sample_tet_report.docx]
A5: FIELD | B5: BIDDER 1 ABC Power (Pvt) Ltd | C5: BIDDER 2 XYZ Energy Solutions | D5: BIDDER 3 Delta Power Ltd
A6: Compliant / Non-compliant (from Table 4) | B6: ='04 Compliance Evaluation'!B15 | C6: ='04 Compliance Evaluation'!C15 | D6: ='04 Compliance Evaluation'!D15
A7: Recommended for Financial Bid Opening (Yes/No) | B7: Yes | C7: No | D7: Yes
A8: Evaluated BOM included? (Yes/No) | B8: Yes | C8: Yes | D8: Yes
A9: Missing price items needing separate sealed envelope? (Yes/No - list items)
A10: Previous purchase price (with period & quantity) | B10: 2024 - 3 units of 60kVA UPS at LKR 3.1M each | C10: 2024 - 3 units of 60kVA UPS at LKR 3.1M each | D10: 2024 - 3 units of 60kVA UPS at LKR 3.1M each
A11: Reference price of similar items (market/previous)
A12: More Suitable (as stated in the TET report) | B12: 1st place | D12: 2nd place
A14: SCORES AND PLACE (calculated on sheet 06 - Procurement Manual Part II, Section 6)
A15: Technical score (/100) | B15: =IF('06 Scores & Ranking'!D36="","",'06 Scores & Ranking'!D36) | C15: =IF('06 Scores & Ranking'!E36="","",'06 Scores & Ranking'!E36) | D15: =IF('06 Scores & Ranking'!F36="","",'06 Scores & Ranking'!F36)
A16: Commercial score (/100) | B16: =IF('06 Scores & Ranking'!D40="","",'06 Scores & Ranking'!D40) | C16: =IF('06 Scores & Ranking'!E40="","",'06 Scores & Ranking'!E40) | D16: =IF('06 Scores & Ranking'!F40="","",'06 Scores & Ranking'!F40)
A17: Final score | B17: =IF('06 Scores & Ranking'!D41="","",'06 Scores & Ranking'!D41) | C17: =IF('06 Scores & Ranking'!E41="","",'06 Scores & Ranking'!E41) | D17: =IF('06 Scores & Ranking'!F41="","",'06 Scores & Ranking'!F41)
A18: PLACE (1st / 2nd / 3rd ...) | B18: =IF('06 Scores & Ranking'!D42="","",'06 Scores & Ranking'!D42) | C18: =IF('06 Scores & Ranking'!E42="","",'06 Scores & Ranking'!E42) | D18: =IF('06 Scores & Ranking'!F42="","",'06 Scores & Ranking'!F42)
A19: Ranking basis | B19: ='06 Scores & Ranking'!B21

Sheet 06 Scores & Ranking
A1: 06 Scores & Ranking (Procurement Manual Part II, Section 6)
A2: Light-blue = calculated (overwrite if needed). Yellow/blue = type here. Place is calculated from the scores.
A4: SCORING SCALES - editable. Source: Procurement Manual Part II, Section 6, 5.1.4 (importance) and 5.1.5 (compliance scale)
A5: Importance | B5: Weight | D5: Degree of compliance | E5: Score
A6: Most Important | B6: 60 | D6: Comply | E6: 10
A7: Important | B7: 30 | D7: Partial Comply | E7: 5
A8: Least Important | B8: 10 | D8: Non Comply | E8: 0
A10: Assumptions (not fixed by the Manual - set per tender before bids open; edit as approved in the tender strategy):
A11: - The four 'Compliance with ... Conditions' rows are pre-scored from Table 4 (Compliant = Comply, Non-compliant = Non Comply). Their importance (Technical = Most, Special = Important, General/Contract = Least) is an assumption.
A12: - Add the tender's own scored criteria in the blank rows (importance + degree of compliance per bidder).
A13: - Technical score = raw score / maximum x 100. Commercial score = lowest eligible price / bidder price x 100 (Attachment A).
A14: - Price weight defaults to 70 : 30 (Part I s.4.7.3, standard equipment); use the weighting approved by TSC / CEO.
A15: - Before prices are known the place is a TECHNICAL ranking only. Per the TET ToR it may be used for commercial weighting only if CEO approval was obtained upfront.
A16: - A bidder marked 'Disqualified' in Table 4 is not ranked (drop-dead criteria, Part I s.4.7.3).
A18: Report: SCMD/TET/2026/014 [sample_tet_report.docx]
A19: Price weighting (%) | B19: 70
A20: Technical weighting (%) | B20: =100-B19
A21: Ranking basis | B21: =IF(AND(COUNT($D$39:$F$39)>0,COUNT($D$39:$F$39)=COUNTIF($D$37:$F$37,"Yes")),"Combined (price + technical)","Technical only (prices not entered yet)")
A23: CRITERION | B23: IMPORTANCE | C23: WEIGHT | D23: BIDDER 1 ABC Power (Pvt) Ltd | E23: BIDDER 2 XYZ Energy Solutions | F23: BIDDER 3 Delta Power Ltd
A24: Compliance with Technical Conditions | B24: Most Important | C24: =IF(B24="","",IFERROR(INDEX($B$6:$B$8,MATCH(B24,$A$6:$A$8,0)),"")) | D24: =IF('04 Compliance Evaluation'!B7="Compliant","Comply",IF('04 Compliance Evaluation'!B7="Non-compliant","Non Comply","")) | E24: =IF('04 Compliance Evaluation'!C7="Compliant","Comply",IF('04 Compliance Evaluation'!C7="Non-compliant","Non Comply","")) | F24: =IF('04 Compliance Evaluation'!D7="Compliant","Comply",IF('04 Compliance Evaluation'!D7="Non-compliant","Non Comply",""))
A25: Compliance with Special Conditions | B25: Important | C25: =IF(B25="","",IFERROR(INDEX($B$6:$B$8,MATCH(B25,$A$6:$A$8,0)),"")) | D25: =IF('04 Compliance Evaluation'!B8="Compliant","Comply",IF('04 Compliance Evaluation'!B8="Non-compliant","Non Comply","")) | E25: =IF('04 Compliance Evaluation'!C8="Compliant","Comply",IF('04 Compliance Evaluation'!C8="Non-compliant","Non Comply","")) | F25: =IF('04 Compliance Evaluation'!D8="Compliant","Comply",IF('04 Compliance Evaluation'!D8="Non-compliant","Non Comply",""))
A26: Compliance with General Conditions | B26: Least Important | C26: =IF(B26="","",IFERROR(INDEX($B$6:$B$8,MATCH(B26,$A$6:$A$8,0)),"")) | D26: =IF('04 Compliance Evaluation'!B6="Compliant","Comply",IF('04 Compliance Evaluation'!B6="Non-compliant","Non Comply","")) | E26: =IF('04 Compliance Evaluation'!C6="Compliant","Comply",IF('04 Compliance Evaluation'!C6="Non-compliant","Non Comply","")) | F26: =IF('04 Compliance Evaluation'!D6="Compliant","Comply",IF('04 Compliance Evaluation'!D6="Non-compliant","Non Comply",""))
A27: Compliance with Contract Conditions | B27: Least Important | C27: =IF(B27="","",IFERROR(INDEX($B$6:$B$8,MATCH(B27,$A$6:$A$8,0)),"")) | D27: =IF('04 Compliance Evaluation'!B9="Compliant","Comply",IF('04 Compliance Evaluation'!B9="Non-compliant","Non Comply","")) | E27: =IF('04 Compliance Evaluation'!C9="Compliant","Comply",IF('04 Compliance Evaluation'!C9="Non-compliant","Non Comply","")) | F27: =IF('04 Compliance Evaluation'!D9="Compliant","Comply",IF('04 Compliance Evaluation'!D9="Non-compliant","Non Comply",""))
C28: =IF(B28="","",IFERROR(INDEX($B$6:$B$8,MATCH(B28,$A$6:$A$8,0)),""))
C29: =IF(B29="","",IFERROR(INDEX($B$6:$B$8,MATCH(B29,$A$6:$A$8,0)),""))
C30: =IF(B30="","",IFERROR(INDEX($B$6:$B$8,MATCH(B30,$A$6:$A$8,0)),""))
C31: =IF(B31="","",IFERROR(INDEX($B$6:$B$8,MATCH(B31,$A$6:$A$8,0)),""))
C32: =IF(B32="","",IFERROR(INDEX($B$6:$B$8,MATCH(B32,$A$6:$A$8,0)),""))
C33: =IF(B33="","",IFERROR(INDEX($B$6:$B$8,MATCH(B33,$A$6:$A$8,0)),""))
A34: Raw score (sum of weight x score) | D34: =SUMPRODUCT($C$24:$C$33,(D24:D33="Comply")*$E$6+(D24:D33="Partial Comply")*$E$7+(D24:D33="Non Comply")*$E$8) | E34: =SUMPRODUCT($C$24:$C$33,(E24:E33="Comply")*$E$6+(E24:E33="Partial Comply")*$E$7+(E24:E33="Non Comply")*$E$8) | F34: =SUMPRODUCT($C$24:$C$33,(F24:F33="Comply")*$E$6+(F24:F33="Partial Comply")*$E$7+(F24:F33="Non Comply")*$E$8)
A35: Maximum possible raw score | D35: =SUM($C$24:$C$33)*$E$6 | E35: =SUM($C$24:$C$33)*$E$6 | F35: =SUM($C$24:$C$33)*$E$6
A36: TECHNICAL SCORE (/100) | D36: =IF(OR(COUNTIF(D24:D33,"?*")=0,D35=0),"",D34/D35*100) | E36: =IF(OR(COUNTIF(E24:E33,"?*")=0,E35=0),"",E34/E35*100) | F36: =IF(OR(COUNTIF(F24:F33,"?*")=0,F35=0),"",F34/F35*100)
A37: Eligible for ranking? (not disqualified) | D37: =IF('04 Compliance Evaluation'!B13="Disqualified","No","Yes") | E37: =IF('04 Compliance Evaluation'!C13="Disqualified","No","Yes") | F37: =IF('04 Compliance Evaluation'!D13="Disqualified","No","Yes")
A38: Evaluated total price (enter when CET prices are known)
A39: Price used for comparison (eligible bidders only) | D39: =IF(AND(ISNUMBER(D38),D37="Yes"),D38,"") | E39: =IF(AND(ISNUMBER(E38),E37="Yes"),E38,"") | F39: =IF(AND(ISNUMBER(F38),F37="Yes"),F38,"")
A40: COMMERCIAL SCORE (/100, lowest eligible price = 100) | D40: =IF(ISNUMBER(D39),MIN($D$39:$F$39)/D39*100,"") | E40: =IF(ISNUMBER(E39),MIN($D$39:$F$39)/E39*100,"") | F40: =IF(ISNUMBER(F39),MIN($D$39:$F$39)/F39*100,"")
A41: FINAL SCORE | D41: =IF(AND(D37="Yes",ISNUMBER(D36)),IF(LEFT($B$21,8)="Combined",$B$19/100*D40+$B$20/100*D36,D36),"") | E41: =IF(AND(E37="Yes",ISNUMBER(E36)),IF(LEFT($B$21,8)="Combined",$B$19/100*E40+$B$20/100*E36,E36),"") | F41: =IF(AND(F37="Yes",ISNUMBER(F36)),IF(LEFT($B$21,8)="Combined",$B$19/100*F40+$B$20/100*F36,F36),"")
A42: PLACE | D42: =IF(ISNUMBER(D41),RANK(D41,$D$41:$F$41)&CHOOSE(IF(AND(MOD(RANK(D41,$D$41:$F$41),100)>=11,MOD(RANK(D41,$D$41:$F$41),100)<=13),0,MOD(RANK(D41,$D$41:$F$41),10))+1,"th","st","nd","rd","th","th","th","th","th","th"),IF(D37="No","Disqualified","")) | E42: =IF(ISNUMBER(E41),RANK(E41,$D$41:$F$41)&CHOOSE(IF(AND(MOD(RANK(E41,$D$41:$F$41),100)>=11,MOD(RANK(E41,$D$41:$F$41),100)<=13),0,MOD(RANK(E41,$D$41:$F$41),10))+1,"th","st","nd","rd","th","th","th","th","th","th"),IF(E37="No","Disqualified","")) | F42: =IF(ISNUMBER(F41),RANK(F41,$D$41:$F$41)&CHOOSE(IF(AND(MOD(RANK(F41,$D$41:$F$41),100)>=11,MOD(RANK(F41,$D$41:$F$41),100)<=13),0,MOD(RANK(F41,$D$41:$F$41),10))+1,"th","st","nd","rd","th","th","th","th","th","th"),IF(F37="No","Disqualified",""))

Sheet Extraction Log
A1: Extraction Log (for the reviewer - not part of the tables)
A3: Source file | B3: Tender-level fields found | C3: Bidders found | D3: Empty bidder cells | E3: Notes
A4: sample_tet_report.docx | B4: 15 of 17 | C4: 3 | D4: 26 of 60 | E4: Evaluated BOM included?: no per-bidder breakdown found - same text copied to every bidder; please split it. Previous purchase price: no per-bidder breakdown found - same text copied to every bidder; please split it. Bidder 1: status set to 'Qualified' because it is recommended for financial opening - please verify. Bidder 3: status set to 'Qualified' because it is recommended for financial opening - please verify. Not found: TET Report Submission Date; Purpose of Tender Scores/place (sheet 06) are calculated from Table 4 compliance and any criteria/prices typed in - the TET report itself is not read for scores.
